[{"contentImagePath":"picture.jpg","contentString":"Hello from Cat","contentId":0,"authorId":1,"timestamp":"2024-12-05T02:35:32.948447700"},{"contentImagePath":"picture2.jpg","contentString":"LOL I AM CRAZY","contentId":1,"authorId":1,"timestamp":"2024-12-05T02:23:24.587292500"},{"contentImagePath":"","contentString":"Beautiful sunset today!","contentId":2,"authorId":2,"timestamp":"2024-12-05T18:45:12.123456789"},{"contentImagePath":"","contentString":"Debugging at 2 AM, wish me luck!","contentId":3,"authorId":3,"timestamp":"2024-12-06T00:15:45.654321"},{"contentImagePath":"","contentString":"Pancakes are the best breakfast.","contentId":4,"authorId":1,"timestamp":"2024-12-05T08:30"},{"contentImagePath":"C:\\Users\\Abdel\\OneDrive\\Pictures\\Mr_bean.jpg","contentString":"Joe da 7ala2","contentId":4370865055388090515,"authorId":1,"timestamp":"2024-12-06T21:17:50.202037"},{"contentImagePath":"C:\\Users\\Abdel\\OneDrive\\Pictures\\Mr_bean.jpg","contentString":"Joe da 7ala2","contentId":8395821567166492325,"authorId":1,"timestamp":"2024-12-06T21:17:50.966295800"},{"contentImagePath":"C:\\Users\\Abdel\\OneDrive\\Pictures\\Mr_bean.jpg","contentString":"Joe da 7ala2","contentId":6259528144068613287,"authorId":1,"timestamp":"2024-12-06T21:17:51.848051100"},{"contentImagePath":"C:\\Users\\Abdel\\OneDrive\\Pictures\\Mr_bean.jpg","contentString":"Joe da 7ala2","contentId":1511097084501889433,"authorId":1,"timestamp":"2024-12-06T21:17:52.702005400"},{"contentImagePath":"","contentString":"Senso mt3sb","contentId":798768947796571415,"authorId":1,"timestamp":"2024-12-06T21:33:42.840194500"},{"contentImagePath":"C:\\Users\\Abdel\\OneDrive\\Pictures\\Temp\\5var_kmap.png","contentString":"Joe howa ely mt3sb","contentId":7891450920838056531,"authorId":1,"timestamp":"2024-12-06T21:37:04.596103900"},{"contentImagePath":"","contentString":"Newest Post","contentId":1415285874960664806,"authorId":1,"timestamp":"2024-12-06T21:43:38.698066900"},{"contentImagePath":"","contentString":"Very new","contentId":3962502439511632288,"authorId":1,"timestamp":"2024-12-06T21:44:28.538387900"},{"contentImagePath":"","contentString":"msh aderrrrrrrrrr","contentId":4401310310281545767,"authorId":1,"timestamp":"2024-12-06T21:50:04.852131900"}]